CHANGES.txt
README.txt
bootstrap.py
buildout.cfg
setup.py
src/zptlint/__init__.py
src/zptlint.egg-info/PKG-INFO
src/zptlint.egg-info/SOURCES.txt
src/zptlint.egg-info/dependency_links.txt
src/zptlint.egg-info/entry_points.txt
src/zptlint.egg-info/requires.txt
src/zptlint.egg-info/top_level.txt
src/zptlint.egg-info/zip-safe