Metadata-Version: 1.0
Name: zptlint
Version: 0.2.4
Summary: Utility to debug Zope Page Templates
Home-page: https://trac.bubblenet.be/browser/bubblenet/pythoncode/zptlint/trunk/README.txt?format=txt
Author: Balazs Ree
Author-email: ree@ree.hu
License: GPL
Keywords: zope
Platform: UNKNOWN
Classifier: Framework :: Zope2
Classifier: Framework :: Zope3
